tc16/__init__.py
tc16/shared/drinkme.txt
tc16/shared/tableaulogo.txt
tc16-1.0.12.dist-info/DESCRIPTION.rst
tc16-1.0.12.dist-info/METADATA
tc16-1.0.12.dist-info/RECORD
tc16-1.0.12.dist-info/WHEEL
tc16-1.0.12.dist-info/entry_points.txt
tc16-1.0.12.dist-info/metadata.json
tc16-1.0.12.dist-info/top_level.txt
