Metadata-Version: 2.0
Name: tc16
Version: 1.0.12
Summary: Make TC16 rad.
Home-page: https://github.com/tableau/tc16
Author: Tableau
Author-email: github@tableau.com
License: MIT
Platform: UNKNOWN
